{"expireTime":9007200836242270000,"key":"gatsby-plugin-mdx-entire-payload-248de4fdc95eea85278e0ff56096427a-","val":{"mdast":{"type":"root","children":[{"type":"import","value":"import DefaultLayout from \"/Users/dennis.okeeffe/Project-Imposter/developer-notes/node_modules/gatsby-theme-docz/src/base/Layout.js\"","position":{"start":{"line":3,"column":1,"offset":2},"end":{"line":3,"column":133,"offset":134},"indent":[]}},{"type":"export","default":true,"value":"export default DefaultLayout","position":{"start":{"line":5,"column":1,"offset":136},"end":{"line":5,"column":29,"offset":164},"indent":[]}},{"type":"heading","depth":1,"children":[{"type":"text","value":"Introduction","position":{"start":{"line":8,"column":3,"offset":169},"end":{"line":8,"column":15,"offset":181},"indent":[]}}],"position":{"start":{"line":8,"column":1,"offset":167},"end":{"line":8,"column":15,"offset":181},"indent":[]}},{"type":"import","value":"import 'katex/dist/katex.min.css';\nimport { BlockMath } from 'react-katex';","position":{"start":{"line":10,"column":1,"offset":183},"end":{"line":11,"column":41,"offset":258},"indent":[1]}},{"type":"heading","depth":2,"children":[{"type":"text","value":"Resources","position":{"start":{"line":13,"column":4,"offset":263},"end":{"line":13,"column":13,"offset":272},"indent":[]}}],"position":{"start":{"line":13,"column":1,"offset":260},"end":{"line":13,"column":13,"offset":272},"indent":[]}},{"type":"list","ordered":true,"start":1,"spread":false,"children":[{"type":"listItem","spread":false,"checked":null,"children":[{"type":"paragraph","children":[{"type":"link","title":null,"url":"https://github.com/talyssonoc/react-katex","children":[{"type":"text","value":"React Katex","position":{"start":{"line":15,"column":5,"offset":278},"end":{"line":15,"column":16,"offset":289},"indent":[]}}],"position":{"start":{"line":15,"column":4,"offset":277},"end":{"line":15,"column":60,"offset":333},"indent":[]}}],"position":{"start":{"line":15,"column":4,"offset":277},"end":{"line":15,"column":60,"offset":333},"indent":[]}}],"position":{"start":{"line":15,"column":1,"offset":274},"end":{"line":15,"column":60,"offset":333},"indent":[]}},{"type":"listItem","spread":false,"checked":null,"children":[{"type":"paragraph","children":[{"type":"link","title":null,"url":"https://en.wikibooks.org/wiki/LaTeX/Mathematics","children":[{"type":"text","value":"LaTex Wikibook","position":{"start":{"line":16,"column":5,"offset":338},"end":{"line":16,"column":19,"offset":352},"indent":[]}}],"position":{"start":{"line":16,"column":4,"offset":337},"end":{"line":16,"column":69,"offset":402},"indent":[]}}],"position":{"start":{"line":16,"column":4,"offset":337},"end":{"line":16,"column":69,"offset":402},"indent":[]}}],"position":{"start":{"line":16,"column":1,"offset":334},"end":{"line":16,"column":69,"offset":402},"indent":[]}}],"position":{"start":{"line":15,"column":1,"offset":274},"end":{"line":16,"column":69,"offset":402},"indent":[1]}},{"type":"heading","depth":2,"children":[{"type":"text","value":"Writing LaTex for the computer","position":{"start":{"line":18,"column":4,"offset":407},"end":{"line":18,"column":34,"offset":437},"indent":[]}}],"position":{"start":{"line":18,"column":1,"offset":404},"end":{"line":18,"column":34,"offset":437},"indent":[]}},{"type":"paragraph","children":[{"type":"text","value":"Using React Katex, we can document the math. Example, ","position":{"start":{"line":20,"column":1,"offset":439},"end":{"line":20,"column":55,"offset":493},"indent":[]}},{"type":"inlineCode","value":"<InlineMath>\\int_0^\\infty x^2 dx</InlineMath>","position":{"start":{"line":20,"column":55,"offset":493},"end":{"line":20,"column":102,"offset":540},"indent":[]}},{"type":"text","value":":","position":{"start":{"line":20,"column":102,"offset":540},"end":{"line":20,"column":103,"offset":541},"indent":[]}}],"position":{"start":{"line":20,"column":1,"offset":439},"end":{"line":20,"column":103,"offset":541},"indent":[]}},{"type":"jsx","value":"<BlockMath>\\int_0^\\infty x^2 dx</BlockMath>","position":{"start":{"line":22,"column":1,"offset":543},"end":{"line":22,"column":44,"offset":586},"indent":[]}},{"type":"export","value":"export const _frontmatter = {}","position":{"start":{"line":25,"column":1,"offset":589},"end":{"line":25,"column":31,"offset":619},"indent":[]}}],"position":{"start":{"line":1,"column":1,"offset":0},"end":{"line":25,"column":31,"offset":619}}},"scopeImports":[],"scopeIdentifiers":[],"rawMDXOutput":"/* @jsx mdx */\nimport { mdx } from '@mdx-js/react';\n/* @jsx mdx */\nimport DefaultLayout from \"/Users/dennis.okeeffe/Project-Imposter/developer-notes/node_modules/gatsby-theme-docz/src/base/Layout.js\"\nimport 'katex/dist/katex.min.css';\nimport { BlockMath } from 'react-katex';\nexport const _frontmatter = {};\nconst makeShortcode = name => function MDXDefaultShortcode(props) {\n  console.warn(\"Component \" + name + \" was not imported, exported, or provided by MDXProvider as global scope\")\n  return <div {...props}/>\n};\n\nconst layoutProps = {\n  _frontmatter\n};\nconst MDXLayout = DefaultLayout\nexport default function MDXContent({\n  components,\n  ...props\n}) {\n  return <MDXLayout {...layoutProps} {...props} components={components} mdxType=\"MDXLayout\">\n\n\n    <h1 {...{\n      \"id\": \"introduction\"\n    }}>{`Introduction`}</h1>\n\n    <h2 {...{\n      \"id\": \"resources\"\n    }}>{`Resources`}</h2>\n    <ol>\n      <li parentName=\"ol\"><a parentName=\"li\" {...{\n          \"href\": \"https://github.com/talyssonoc/react-katex\"\n        }}>{`React Katex`}</a></li>\n      <li parentName=\"ol\"><a parentName=\"li\" {...{\n          \"href\": \"https://en.wikibooks.org/wiki/LaTeX/Mathematics\"\n        }}>{`LaTex Wikibook`}</a></li>\n    </ol>\n    <h2 {...{\n      \"id\": \"writing-latex-for-the-computer\"\n    }}>{`Writing LaTex for the computer`}</h2>\n    <p>{`Using React Katex, we can document the math. Example, `}<inlineCode parentName=\"p\">{`<InlineMath>\\\\int_0^\\\\infty x^2 dx</InlineMath>`}</inlineCode>{`:`}</p>\n    <BlockMath mdxType=\"BlockMath\">\\int_0^\\infty x^2 dx</BlockMath>\n\n    </MDXLayout>;\n}\n\n;\nMDXContent.isMDXComponent = true;"}}