{"expireTime":9007200836242254000,"key":"gatsby-plugin-mdx-entire-payload-0b75bccd605c32add2e0e2d3c691e40f-","val":{"mdast":{"type":"root","children":[{"type":"import","value":"import DefaultLayout from \"/Users/dennis.okeeffe/Project-Imposter/developer-notes/node_modules/gatsby-theme-docz/src/base/Layout.js\"","position":{"start":{"line":3,"column":1,"offset":2},"end":{"line":3,"column":133,"offset":134},"indent":[]}},{"type":"export","default":true,"value":"export default DefaultLayout","position":{"start":{"line":5,"column":1,"offset":136},"end":{"line":5,"column":29,"offset":164},"indent":[]}},{"type":"heading","depth":1,"children":[{"type":"text","value":"React Native Help Sheet","position":{"start":{"line":7,"column":3,"offset":168},"end":{"line":7,"column":26,"offset":191},"indent":[]}}],"position":{"start":{"line":7,"column":1,"offset":166},"end":{"line":7,"column":26,"offset":191},"indent":[]}},{"type":"heading","depth":2,"children":[{"type":"text","value":"RNHELP-1: Debugger","position":{"start":{"line":9,"column":4,"offset":196},"end":{"line":9,"column":22,"offset":214},"indent":[]}}],"position":{"start":{"line":9,"column":1,"offset":193},"end":{"line":9,"column":22,"offset":214},"indent":[]}},{"type":"paragraph","children":[{"type":"text","value":"To stop the React Native dev menu from showing up, ensure that you put into ","position":{"start":{"line":11,"column":1,"offset":216},"end":{"line":11,"column":77,"offset":292},"indent":[]}},{"type":"inlineCode","value":"Release","position":{"start":{"line":11,"column":77,"offset":292},"end":{"line":11,"column":86,"offset":301},"indent":[]}}],"position":{"start":{"line":11,"column":1,"offset":216},"end":{"line":11,"column":86,"offset":301},"indent":[]}},{"type":"heading","depth":2,"children":[{"type":"text","value":"RNHELP-2: (void) casting for iOS10","position":{"start":{"line":13,"column":4,"offset":306},"end":{"line":13,"column":38,"offset":340},"indent":[]}}],"position":{"start":{"line":13,"column":1,"offset":303},"end":{"line":13,"column":38,"offset":340},"indent":[]}},{"type":"code","lang":null,"meta":null,"value":"(void)SecRandomCopyBytes(kSecRandomDefault, keyBytes.length, keyBytes.mutableBytes);\n(void)SecRandomCopyBytes(kSecRandomDefault, sizeof(uint32_t), (uint8_t *)mask_key);","position":{"start":{"line":15,"column":1,"offset":342},"end":{"line":18,"column":4,"offset":518},"indent":[1,1,1]}},{"type":"heading","depth":2,"children":[{"type":"text","value":"RNHELP-3: Code Signing","position":{"start":{"line":20,"column":4,"offset":523},"end":{"line":20,"column":26,"offset":545},"indent":[]}}],"position":{"start":{"line":20,"column":1,"offset":520},"end":{"line":20,"column":26,"offset":545},"indent":[]}},{"type":"paragraph","children":[{"type":"text","value":"If disallowed for build, turn off automatic signing, clean, close the project, up back up and then turn automatic signing back on.","position":{"start":{"line":22,"column":1,"offset":547},"end":{"line":22,"column":131,"offset":677},"indent":[]}}],"position":{"start":{"line":22,"column":1,"offset":547},"end":{"line":22,"column":131,"offset":677},"indent":[]}},{"type":"export","value":"export const _frontmatter = {}","position":{"start":{"line":25,"column":1,"offset":680},"end":{"line":25,"column":31,"offset":710},"indent":[]}}],"position":{"start":{"line":1,"column":1,"offset":0},"end":{"line":25,"column":31,"offset":710}}},"scopeImports":[],"scopeIdentifiers":[],"rawMDXOutput":"/* @jsx mdx */\nimport { mdx } from '@mdx-js/react';\n/* @jsx mdx */\nimport DefaultLayout from \"/Users/dennis.okeeffe/Project-Imposter/developer-notes/node_modules/gatsby-theme-docz/src/base/Layout.js\"\nexport const _frontmatter = {};\nconst makeShortcode = name => function MDXDefaultShortcode(props) {\n  console.warn(\"Component \" + name + \" was not imported, exported, or provided by MDXProvider as global scope\")\n  return <div {...props}/>\n};\n\nconst layoutProps = {\n  _frontmatter\n};\nconst MDXLayout = DefaultLayout\nexport default function MDXContent({\n  components,\n  ...props\n}) {\n  return <MDXLayout {...layoutProps} {...props} components={components} mdxType=\"MDXLayout\">\n\n\n    <h1 {...{\n      \"id\": \"react-native-help-sheet\"\n    }}>{`React Native Help Sheet`}</h1>\n    <h2 {...{\n      \"id\": \"rnhelp-1-debugger\"\n    }}>{`RNHELP-1: Debugger`}</h2>\n    <p>{`To stop the React Native dev menu from showing up, ensure that you put into `}<inlineCode parentName=\"p\">{`Release`}</inlineCode></p>\n    <h2 {...{\n      \"id\": \"rnhelp-2-void-casting-for-ios10\"\n    }}>{`RNHELP-2: (void) casting for iOS10`}</h2>\n    <pre><code parentName=\"pre\" {...{}}>{`(void)SecRandomCopyBytes(kSecRandomDefault, keyBytes.length, keyBytes.mutableBytes);\n(void)SecRandomCopyBytes(kSecRandomDefault, sizeof(uint32_t), (uint8_t *)mask_key);\n`}</code></pre>\n    <h2 {...{\n      \"id\": \"rnhelp-3-code-signing\"\n    }}>{`RNHELP-3: Code Signing`}</h2>\n    <p>{`If disallowed for build, turn off automatic signing, clean, close the project, up back up and then turn automatic signing back on.`}</p>\n\n    </MDXLayout>;\n}\n\n;\nMDXContent.isMDXComponent = true;"}}